txttoqti/__init__.py
txttoqti/cli.py
txttoqti/converter.py
txttoqti/exceptions.py
txttoqti/logging_config.py
txttoqti/models.py
txttoqti/parser.py
txttoqti/qti_generator.py
txttoqti/smart_converter.py
txttoqti/txttoqti.py
txttoqti/utils.py
txttoqti/validator.py
txttoqti/educational/__init__.py
txttoqti/educational/cli.py
txttoqti/educational/converter.py
txttoqti/educational/detector.py
txttoqti/educational/formats.py
txttoqti/educational/utils.py
txttoqti-0.5.0.dist-info/METADATA
txttoqti-0.5.0.dist-info/WHEEL
txttoqti-0.5.0.dist-info/entry_points.txt
txttoqti-0.5.0.dist-info/licenses/LICENSE
txttoqti-0.5.0.dist-info/RECORD
