Metadata-Version: 2.4
Name: txttoqti
Version: 0.5.0
Summary: Universal converter that transforms text-based question banks into QTI packages compatible with Canvas LMS
Project-URL: Homepage, https://github.com/julihocc/txttoqti
Project-URL: Documentation, https://github.com/julihocc/txttoqti#readme
Project-URL: Repository, https://github.com/julihocc/txttoqti
Project-URL: Issues, https://github.com/julihocc/txttoqti/issues
Project-URL: Changelog, https://github.com/julihocc/txttoqti/releases
Author-email: "Juliho C.C." <julihocc@yahoo.com>
License: MIT
License-File: LICENSE
Keywords: assessment,canvas,education,lms,qti,quiz
Classifier: Development Status :: 3 - Alpha
Classifier: Intended Audience :: Education
Classifier: License :: OSI Approved :: MIT License
Classifier: Programming Language :: Python :: 3
Classifier: Programming Language :: Python :: 3.10
Classifier: Programming Language :: Python :: 3.11
Classifier: Programming Language :: Python :: 3.12
Classifier: Topic :: Education
Classifier: Topic :: Text Processing :: Markup :: XML
Requires-Python: >=3.10
Provides-Extra: dev
Requires-Dist: black>=23.0; extra == 'dev'
Requires-Dist: flake8>=6.0; extra == 'dev'
Requires-Dist: mypy>=1.0; extra == 'dev'
Requires-Dist: pre-commit>=3.0; extra == 'dev'
Requires-Dist: pytest-cov>=4.0; extra == 'dev'
Requires-Dist: pytest>=7.0; extra == 'dev'
Provides-Extra: test
Requires-Dist: pytest-cov>=4.0; extra == 'test'
Requires-Dist: pytest>=7.0; extra == 'test'
